pyimagevideo/__init__.py
pyimagevideo/imagemultipage.py
pyimagevideo-0.6.0.data/scripts/Demo_FPS_matplotlib_image.py
pyimagevideo-0.6.0.data/scripts/Demo_localBinaryPattern.py
pyimagevideo-0.6.0.data/scripts/HDF5_to_AVI.py
pyimagevideo-0.6.0.data/scripts/RGB_BGR_GBR_conv.py
pyimagevideo-0.6.0.data/scripts/audio_oct2py.py
pyimagevideo-0.6.0.data/scripts/audio_pyaudio.py
pyimagevideo-0.6.0.data/scripts/audio_pygame.py
pyimagevideo-0.6.0.data/scripts/audio_pysounddevice.py
pyimagevideo-0.6.0.data/scripts/demo_findpeaks.py
pyimagevideo-0.6.0.data/scripts/imageconv.py
pyimagevideo-0.6.0.data/scripts/readAVI_imageio.py
pyimagevideo-0.6.0.data/scripts/readAVI_opencv.py
pyimagevideo-0.6.0.data/scripts/readAVIs_opencv.py
pyimagevideo-0.6.0.data/scripts/scipyByteScaleBug.py
pyimagevideo-0.6.0.data/scripts/wavelength2rgb.py
pyimagevideo-0.6.0.data/scripts/writeAVI_imageio.py
pyimagevideo-0.6.0.data/scripts/writeAVI_matplotlib.py
pyimagevideo-0.6.0.data/scripts/writeAVI_opencv.py
pyimagevideo-0.6.0.dist-info/METADATA
pyimagevideo-0.6.0.dist-info/RECORD
pyimagevideo-0.6.0.dist-info/WHEEL
pyimagevideo-0.6.0.dist-info/top_level.txt
