Metadata-Version: 2.1
Name: pyimagevideo
Version: 0.6.0
Summary: Demos of OpenCV, read/write videos, etc.
Home-page: https://github.com/scivision/pyimagevideo
Author: Michael Hirsch, Ph.D.
License: UNKNOWN
Platform: UNKNOWN
Classifier: Development Status :: 4 - Beta
Classifier: Environment :: Console
Classifier: Intended Audience :: Developers
Classifier: Intended Audience :: Education
Classifier: License :: OSI Approved :: MIT License
Classifier: Operating System :: OS Independent
Classifier: Programming Language :: Python :: 3.6
Classifier: Programming Language :: Python :: 3.7
Classifier: Topic :: Multimedia :: Graphics :: 3D Rendering
Classifier: Topic :: Multimedia :: Graphics :: Presentation
Classifier: Topic :: Multimedia :: Graphics :: Viewers
Classifier: Topic :: Multimedia :: Sound/Audio :: Players
Classifier: Topic :: Scientific/Engineering :: Visualization
Requires-Python: >=3.6
Provides-Extra: tests
Provides-Extra: io
Provides-Extra: audio
Requires-Dist: numpy
Requires-Dist: scipy
Requires-Dist: imageio (>=2.3)
Requires-Dist: scikit-image
Requires-Dist: matplotlib (>=2.2)
Provides-Extra: audio
Provides-Extra: io
Requires-Dist: h5py; extra == 'io'
Requires-Dist: scipy; extra == 'io'
Requires-Dist: morecvutils; extra == 'io'
Provides-Extra: tests
Requires-Dist: pytest; extra == 'tests'
Requires-Dist: coveralls; extra == 'tests'
Requires-Dist: flake8; extra == 'tests'
Requires-Dist: mypy; extra == 'tests'
